emproto/__init__.py
emproto/encryption.py
emproto/transport.py
emproto-1.2.dist-info/METADATA
emproto-1.2.dist-info/WHEEL
emproto-1.2.dist-info/top_level.txt
emproto-1.2.dist-info/RECORD
