Metadata-Version: 2.2
Name: emproto
Version: 1.2
Summary: Bezpečný přenos zpráv a souborů přes šifrování
Home-page: https://github.com/certikpolik30/emproto
Author: Alfisene Keita
Classifier: Programming Language :: Python :: 3
Classifier: License :: OSI Approved :: MIT License
Classifier: Operating System :: OS Independent
Requires-Dist: cryptography
Dynamic: author
Dynamic: classifier
Dynamic: home-page
Dynamic: requires-dist
Dynamic: summary
